regfile.vhd
library ieee;
use ieee.std_logic_1164.all;

--WS = Register Write
entity regfile is
  port(
    RS1,RS2,WS : in std_logic_vector(1 downto 0);
    Write_Data : in std_logic_vector(7 downto 0);
    CLK : in std_logic;
    WE : in std_logic;
    RS1_data,RS2_data : out std_logic_vector(7 downto 0)
  );
end entity regfile;

--Initialize 4 registers and set each of their values to 0
architecture behavioral of regfile is

signal Reg0,Reg1,Reg2,Reg3 : std_logic_vector(7 downto 0) := "00000000";
  
--The registers are addressed from b00 to b11
  begin
    with RS1 select RS1_data <=
      Reg0 when "00",
      Reg1 when "01",
      Reg2 when "10",
      Reg3 when others;
    with RS2 select RS2_data <=
      Reg0 when "00",
      Reg1 when "01",
      Reg2 when "10",
      Reg3 when others;

--The condition will be true only on rising edge of the CLK signal
    process (CLK) is
      begin
        if (CLK'event and CLK='1') then
          if (WE = '1') then
            if (WS = "00") then
              Reg0 <= Write_Data;
            elsif (WS = "01") then
              Reg1 <= Write_Data;
            elsif (WS = "10") then
              Reg2 <= Write_Data;
            elsif (WS = "11") then
              Reg3 <= Write_Data;
            end if;
          end if;
        end if;
      end process;
    end architecture;

reg_tb.vhdl
library ieee;
use ieee.std_logic_1164.all;

--  A testbench has no ports.
entity reg_tb is
end reg_tb;

architecture behav of reg_tb is
--  Declaration of the component that will be instantiated.
component regfile
port (		RS1: 		in std_logic_vector(1 downto 0);
		RS2:       	in std_logic_vector(1 downto 0);
		WS:		in std_logic_vector(1 downto 0);
		
		WE:		in std_logic;
		Write_Data:	in std_logic_vector(7 downto 0);
		CLK:		in std_logic;
		
		RS1_data:	out std_logic_vector(7 downto 0);
		RS2_data:	out std_logic_vector(7 downto 0)		
);
end component;

signal RS1,RS2,WS : std_logic_vector(1 downto 0);
signal WE,CLK : std_logic;
signal Write_Data,RS1_data,RS2_data : std_logic_vector(7 downto 0);

begin
--  Component instantiation.
R1 : regfile
	port map(
		RS1=>RS1,
		RS2=>RS2,
		WS=>WS,
		WE=>WE,
		Write_data=>Write_data,
		CLK=>CLK,
		RS1_data=>RS1_data,
		RS2_data=>RS2_data
	);
	
--  This process does the real job.
process

type pattern_type is record
RS1: std_logic_vector(1 downto 0);
RS2: std_logic_vector(1 downto 0);
WS : std_logic_vector(1 downto 0);
WE: std_logic;
CLK : std_logic;
Write_Data: std_logic_vector(7 downto 0);
RS1_data: std_logic_vector(7 downto 0);
RS2_data : std_logic_vector(7 downto 0);

end record;

--RS1,RS2,WS,WE,clk,WD,RS1D,RS2D
type pattern_array is array (natural range <>) of pattern_type;
constant patterns : pattern_array :=

(("00","00","00",'0','0',"00101101","00000000","00000000"), -- Clock not enabled so do nothing
("00","00","00",'0','1',"00101101","00000000","00000000"), -- Write not enabled so do nothing
("00","00","00",'1','0',"00101101","00000000","00000000"), -- Clock not enabled so do nothing
("00","00","00",'1','1',"00101101","00101101","00101101"), -- WE '1' so WS'00 means write data ro RS1'00 and RS2'00
("11","00","10",'1','0',"10100001","00000000","00101101"), -- Clock not enabled so do nothing
("01","10","10",'1','1',"10100001","00000000","10100001"), -- WE '1' and WS'10 so write data to RS1'10 and RS2'10
("10","00","01",'1','0',"00101101","10100001","00101101"), -- Clock not enabled so do nothing
("01","11","01",'1','1',"00000001","00000001","00000000"), -- WE '1' and WS'01 so write data to RS1'01 and RS2'01
("11","01","11",'1','0',"00101101","00000000","00000001"), -- Clock not enabled so do nothing
("00","10","11",'1','1',"11101101","00101101","10100001"), -- WE '1' and WS'11 so write data to RS1'11 and RS2'11
("01","00","00",'1','0',"10100101","00000001","00101101"), -- Clock not enabled so do nothing
("01","00","00",'1','1',"10100101","00000001","10100101"), -- WE '1' and WS'00 so overwrite data at RS1'00 and RS2'00
 
 -- WE '0' for this block so just read will be performed here
("00","11","00",'0','0',"11111111","10100101","11101101"), -- Clock not enabled so do nothing
("00","11","00",'0','1',"11111111","10100101","11101101"), -- Read RS1'00 and RS2'11
("01","10","00",'0','0',"11111111","00000001","10100001"), -- Clock not enabled so do nothing
("01","10","01",'0','1',"11111111","00000001","10100001"), -- Read RS1'01 and RS2'10
("10","01","00",'0','0',"11111111","10100001","00000001"), -- Clock not enabled so do nothing
("10","01","10",'0','1',"11111111","10100001","00000001"), -- Read RS1'10 and RS2'01
("11","00","00",'0','0',"11111111","11101101","10100101"), -- Clock not enabled so do nothing
("11","00","11",'0','1',"11111111","11101101","10100101")  -- Read RS1'11 and RS2'00
);

begin
--  Check each pattern.
for n in patterns'range loop
--  Set the inputs.
RS1 <= patterns(n).RS1;
RS2 <= patterns(n).RS2;
WS <= patterns(n).WS;

CLK <= patterns(n).CLK;
WE <= patterns(n).WE;
Write_Data <= patterns(n).Write_Data;


--  Wait for the results.
wait for 1 ns;
--  Check the outputs.
assert RS1_data = patterns(n).RS1_data
report "Register 1 is wrong" severity error;
assert RS2_data = patterns(n).RS2_data
report "Register 2 is wrong" severity error;

end loop;
assert false report "end of test" severity note;
--  Wait forever; this will finish the simulation.
wait;
end process;
end behav;

regfile.vcd
$date
  Fri May 15 17:37:28 2020
$end
$version
  GHDL v0
$end
$timescale
  1 fs
$end
$scope module standard $end
$upscope $end
$scope module std_logic_1164 $end
$upscope $end
$scope module reg_tb $end
$var reg 2 ! rs1[1:0] $end
$var reg 2 " rs2[1:0] $end
$var reg 2 # ws[1:0] $end
$var reg 1 $ we $end
$var reg 1 % clk $end
$var reg 8 & write_data[7:0] $end
$var reg 8 ' rs1_data[7:0] $end
$var reg 8 ( rs2_data[7:0] $end
$scope module r1 $end
$var reg 2 ) rs1[1:0] $end
$var reg 2 * rs2[1:0] $end
$var reg 2 + ws[1:0] $end
$var reg 8 , write_data[7:0] $end
$var reg 1 - clk $end
$var reg 1 . we $end
$var reg 8 / rs1_data[7:0] $end
$var reg 8 0 rs2_data[7:0] $end
$var reg 8 1 reg0[7:0] $end
$var reg 8 2 reg1[7:0] $end
$var reg 8 3 reg2[7:0] $end
$var reg 8 4 reg3[7:0] $end
$upscope $end
$upscope $end
$enddefinitions $end
#0
b00 !
b00 "
b00 #
0$
0%
b00101101 &
b00000000 '
b00000000 (
b00 )
b00 *
b00 +
b00101101 ,
0-
0.
b00000000 /
b00000000 0
b00000000 1
b00000000 2
b00000000 3
b00000000 4
#1000000
1%
1-
#2000000
1$
0%
0-
1.
#3000000
1%
b00101101 '
b00101101 (
1-
b00101101 /
b00101101 0
b00101101 1
#4000000
b11 !
b10 #
0%
b10100001 &
b00000000 '
b11 )
b10 +
b10100001 ,
0-
b00000000 /
#5000000
b01 !
b10 "
1%
b10100001 (
b01 )
b10 *
1-
b10100001 0
b10100001 3
#6000000
b10 !
b00 "
b01 #
0%
b00101101 &
b10100001 '
b00101101 (
b10 )
b00 *
b01 +
b00101101 ,
0-
b10100001 /
b00101101 0
#7000000
b01 !
b11 "
1%
b00000001 &
b00000001 '
b00000000 (
b01 )
b11 *
b00000001 ,
1-
b00000001 /
b00000000 0
b00000001 2
#8000000
b11 !
b01 "
b11 #
0%
b00101101 &
b00000000 '
b00000001 (
b11 )
b01 *
b11 +
b00101101 ,
0-
b00000000 /
b00000001 0
#9000000
b00 !
b10 "
1%
b11101101 &
b00101101 '
b10100001 (
b00 )
b10 *
b11101101 ,
1-
b00101101 /
b10100001 0
b11101101 4
#10000000
b01 !
b00 "
b00 #
0%
b10100101 &
b00000001 '
b00101101 (
b01 )
b00 *
b00 +
b10100101 ,
0-
b00000001 /
b00101101 0
#11000000
1%
b10100101 (
1-
b10100101 0
b10100101 1
#12000000
b00 !
b11 "
0$
0%
b11111111 &
b10100101 '
b11101101 (
b00 )
b11 *
b11111111 ,
0-
0.
b10100101 /
b11101101 0
#13000000
1%
1-
#14000000
b01 !
b10 "
0%
b00000001 '
b10100001 (
b01 )
b10 *
0-
b00000001 /
b10100001 0
#15000000
b01 #
1%
b01 +
1-
#16000000
b10 !
b01 "
b00 #
0%
b10100001 '
b00000001 (
b10 )
b01 *
b00 +
0-
b10100001 /
b00000001 0
#17000000
b10 #
1%
b10 +
1-
#18000000
b11 !
b00 "
b00 #
0%
b11101101 '
b10100101 (
b11 )
b00 *
b00 +
0-
b11101101 /
b10100101 0
#19000000
b11 #
1%
b11 +
1-
